{
  "c7656143bb9229fba4e131863863506d": {
    "title": "Infrastructure race accelerates at India-China border",
    "date": "2026-01-06",
    "seen_on": "2026-03-22"
  },
  "fa719999638df83d4a687206ff3f549f": {
    "title": "China’s dispute with India over Arunachal Pradesh",
    "date": "2025-12-17",
    "seen_on": "2026-03-22"
  },
  "76efd9ee96f51bb57103ca882e0f311c": {
    "title": "India-Pakistan conflict",
    "date": "2026-03-12",
    "seen_on": "2026-03-22"
  },
  "920ffbcfb4d96698f899cdb9670d6911": {
    "title": "Did Ali Khamenei support PM Modi after abrogation of Article 370, and what has b",
    "date": "2026-03-02",
    "seen_on": "2026-03-22"
  },
  "dd2e982cfb5389d1b7cedc8c5a4b490b": {
    "title": "Sri Lanka Playbook: India’s Strategic Gains Over China",
    "date": "2026-03-19",
    "seen_on": "2026-03-22"
  },
  "316ea15d38f232ae716db5821e1c07aa": {
    "title": "US & India Prepare to Grab Hambantota Port Claiming It’s a Chinese Base",
    "date": "2026-03-19",
    "seen_on": "2026-03-22"
  },
  "ac0c74e746b39011826358a826053516": {
    "title": "India-China push to resume Lipulekh trade reignites Nepal’s concerns",
    "date": "2026-03-22",
    "seen_on": "2026-03-22"
  },
  "0ebc97abefecdecced5280ef83ae5f44": {
    "title": "India, China set to revive trade via Lipulekh after 6 years: Why Nepal is opposi",
    "date": "2026-03-20",
    "seen_on": "2026-03-22"
  },
  "dad3f5cad57f01df148b5a03b3203407": {
    "title": "Is the Ice Finally Breaking in Bangladesh-India Relations?",
    "date": "2026-03-16",
    "seen_on": "2026-03-22"
  },
  "8ce0ed3b3f26ad853274d8284f283e90": {
    "title": "Grey Waves: India Confronts China’s Hybrid Maritime Strategy",
    "date": "2026-03-19",
    "seen_on": "2026-03-22"
  },
  "097256ddecc110a45d59f43d167127ef": {
    "title": "Navy monitors every Chinese ship entering Indian Ocean Region, says Navy Vice-Ch",
    "date": "2025-10-31",
    "seen_on": "2026-03-22"
  },
  "29aa3804df42a74e9f863434a102d818": {
    "title": "Gen Naravane’s Other China Revelation: How It Targeted India Via Bhutan",
    "date": "2026-02-08",
    "seen_on": "2026-03-22"
  },
  "f7daab729fd284c4be00cf2b0af7d603": {
    "title": "India, China, and the Early Harvest: Understanding Bhutan’s Border Bet",
    "date": "2025-10-15",
    "seen_on": "2026-03-22"
  },
  "c34d79fbc536615847918f26e67bc025": {
    "title": "The War on Iran Comes to the Indian Ocean",
    "date": "2026-03-18",
    "seen_on": "2026-03-22"
  },
  "e593762f138a5d522466b7334e673445": {
    "title": "India won’t abandon Iran, but its western strategy is under strain - opinion",
    "date": "2026-03-20",
    "seen_on": "2026-03-22"
  },
  "593824ba49448371b756e5ec362bd5ca": {
    "title": "Can the Quad regain momentum after the India–US reset?",
    "date": "2026-02-17",
    "seen_on": "2026-03-22"
  },
  "00ef4b9c464ea624290af29e9dd43331": {
    "title": "Japan-Australia-India-U.S. (Quad) meetings",
    "date": "2025-12-18",
    "seen_on": "2026-03-22"
  },
  "419a5f8c6d5c0281304233f219b83d94": {
    "title": "India's strategic response to the Belt and Road Initiative",
    "date": "2025-11-08",
    "seen_on": "2026-03-22"
  },
  "2654324be5654172e3ae8aa44ba2a7cc": {
    "title": "India-China in new spat over Arunachal Pradesh: What’s it all about?",
    "date": "2025-11-26",
    "seen_on": "2026-03-22"
  },
  "485e6714aeae2f8dbf6f4fa1162d954c": {
    "title": "How India Quietly Offset China’s ‘String of Pearls’ With a Network of Overseas M",
    "date": "2025-12-24",
    "seen_on": "2026-03-22"
  },
  "05d5e520a093ac9182d51342c86e9b1c": {
    "title": "India approves limited easing of Chinese investment curbs after years of frictio",
    "date": "2026-03-10",
    "seen_on": "2026-03-22"
  },
  "f0a097f21514a25e8571226609914729": {
    "title": "Semiconductor Industry in India: Incentives and Key Players",
    "date": "2026-03-13",
    "seen_on": "2026-03-22"
  },
  "ba255aec20a382d82256c6e9fd42e858": {
    "title": "India emerges as design hub in global chip supply chain shift",
    "date": "2026-03-18",
    "seen_on": "2026-03-22"
  },
  "73694c44aa648f89b4b2e88a0a6fd1d5": {
    "title": "India can play key role in breaking China's near-monopoly on critical minerals",
    "date": "2026-03-22",
    "seen_on": "2026-03-22"
  },
  "adbc8e7bb5d2dd01c11b81b960ea92ca": {
    "title": "Japan in talks with India to explore for rare earths, sources say",
    "date": "2026-03-03",
    "seen_on": "2026-03-22"
  },
  "de494647b28ddc0c1fb103c2e3982089": {
    "title": "Strait of Hormuz & India's Oil Supply: Import Dependencies & Mitigation Measures",
    "date": "2026-03-16",
    "seen_on": "2026-03-22"
  },
  "a9ca9de4d258c474c1dc396a949aca8f": {
    "title": "Gulf War 3.0: How Is India Securing Its Oil Supplies?",
    "date": "2026-03-16",
    "seen_on": "2026-03-22"
  },
  "f9baf2bd4cfba39665549f840023f7c5": {
    "title": "US lawmakers flag China’s growing debt influence in India’s neighbourhood - The ",
    "date": "2026-03-22",
    "seen_on": "2026-03-22"
  },
  "29dd610976dc7eb0161b94962c17891a": {
    "title": "Nascent China-linked cyberespionage campaign hits India",
    "date": "2026-01-26",
    "seen_on": "2026-03-22"
  },
  "54048f5deb6400416d8b207249d9c744": {
    "title": "India Under Cyber Attack: Evasive Panda Spies Through Fake App Updates, Steals D",
    "date": "2026-01-09",
    "seen_on": "2026-03-22"
  },
  "78e9bd58a0a0fbc2582147f48962ccc4": {
    "title": "Where Does India Stand in the Global AI Race?",
    "date": "2026-02-24",
    "seen_on": "2026-03-22"
  },
  "d681f2a3add916dc304ef5940408b036": {
    "title": "Global AI Race: Comparative Strategies of the US, China, and India",
    "date": "2026-02-06",
    "seen_on": "2026-03-22"
  },
  "d92a634f47b49bfc9d8ecd4a2cafdee8": {
    "title": "22 Years Of Indian Space Wonders: A Chinese Journalist’s Front-Row View Of ISRO ",
    "date": "2025-12-26",
    "seen_on": "2026-03-22"
  },
  "cfedb80dfcd86a567d9aac4d394d3028": {
    "title": "ISRO presents model of Indian space station for the first time, will compete wit",
    "date": "2025-08-23",
    "seen_on": "2026-03-22"
  },
  "9bc6e5b8768d9c60145e9b252d265d78": {
    "title": "Improving India–China ties unlikely to bring immediate relief to Huawei and ZTE",
    "date": "2025-09-03",
    "seen_on": "2026-03-22"
  },
  "25c97ecefd537249aaf279ddd7048339": {
    "title": "'Water bomb': China building world's most powerful mega dam in the Himalayas — h",
    "date": "2026-03-18",
    "seen_on": "2026-03-22"
  },
  "8e301834cc89e95e809a014cba239b5f": {
    "title": "India and China in deep water over Himalayan hydropower",
    "date": "2025-12-15",
    "seen_on": "2026-03-22"
  },
  "dcb46be4d0100f75aea9bd02d62988a7": {
    "title": "Shrinking Himalayan Glaciers Threaten Chinese and Indian Energy Transitions",
    "date": "2022-12-17",
    "seen_on": "2026-03-22"
  },
  "4edc41b416fcec427f06405e41f27b73": {
    "title": "Is India-China race to build damaging the Himalayas?",
    "date": "2023-03-12",
    "seen_on": "2026-03-22"
  },
  "645bff3574bb5769fa6eb631a6b84fa6": {
    "title": "Changing Climate Is Impacting India’s Nutrition Security",
    "date": "2025-12-17",
    "seen_on": "2026-03-22"
  },
  "37acbc0380d4694f0425aa0fcc12a211": {
    "title": "India’s power capacity to double to 1,121 GW by 2035-36 as solar leads energy tr",
    "date": "2026-03-19",
    "seen_on": "2026-03-22"
  },
  "066ed328994b305f8eb6ca67c0c69ae4": {
    "title": "India’s Renewable Energy Leap, Solar to Quadruple",
    "date": "2026-03-19",
    "seen_on": "2026-03-22"
  },
  "3cb2a4525177551802e4826302c8b7b9": {
    "title": "2025 in Protest: Across issues, across India",
    "date": "2026-02-16",
    "seen_on": "2026-03-22"
  },
  "9ee0bc6b73394ef7297f170dee420af9": {
    "title": "How three Uyghur brothers fled China – to spend 12 years in an Indian prison",
    "date": "2025-12-05",
    "seen_on": "2026-03-22"
  },
  "08030bb8da757eb03e2556dac0f16fb2": {
    "title": "CPEC’s Afghan push poses a new challenge for India",
    "date": "2025-10-07",
    "seen_on": "2026-03-22"
  },
  "50071e8855d5f4049b2949dc8dc03297": {
    "title": "500% Trump Tariffs? India could pay the price on Russian oil sanctions while Chi",
    "date": "2026-01-08",
    "seen_on": "2026-03-22"
  },
  "e5bcd3b85f2c5b1278c0176b8652ec19": {
    "title": "Watch: Can India compete with China in rare earths? | Data Point",
    "date": "2026-02-27",
    "seen_on": "2026-03-22"
  },
  "243acf81615bb99151229dc53e9d98e6": {
    "title": "Geo-strategic calculus of Pakistan and India",
    "date": "2025-11-28",
    "seen_on": "2026-03-22"
  },
  "303053bc340e6c9e5a202da1e881cb39": {
    "title": "Research Article: The securitization of the Rohingya in India’s shifting refugee",
    "date": "2025-10-07",
    "seen_on": "2026-03-22"
  },
  "7b20b06b0d0ed7011659a357ecaa000d": {
    "title": "Conflict Between India and Pakistan | Global Conflict Tracker",
    "date": "2026-02-18",
    "seen_on": "2026-03-23"
  },
  "244390b65e760db56e88e9f6a180b022": {
    "title": "Muizzu's U-turn: India in, China out? Maldives seemingly pivots again as PM Modi",
    "date": "2026-03-17",
    "seen_on": "2026-03-23"
  },
  "b49eab4b79772d0e6eae56a337081b95": {
    "title": "China tightening footprint around India, warns Chief of Integrated Defence Staff",
    "date": "2026-03-11",
    "seen_on": "2026-03-23"
  },
  "61042d33d88105d9c105b5e9c897d5b7": {
    "title": "India and Sanctions on Russian Energy: Policy Response and Future Options",
    "date": "2025-10-21",
    "seen_on": "2026-03-23"
  },
  "9e0860db9227eb4ac714ea2727546e92": {
    "title": "The Evolving Semiconductor Supply Chain Landscape: Lessons for India’s Semicondu",
    "date": "2025-12-29",
    "seen_on": "2026-03-23"
  },
  "43f01ef762372a61a2802a5e5129aed2": {
    "title": "Tibet in India’s China Calculus",
    "date": "2026-03-10",
    "seen_on": "2026-03-23"
  },
  "9bb24fd49a37ac104c03cce5117322b1": {
    "title": "‘What’s our fault?’: India’s expulsion of Pakistanis still splits families",
    "date": "2025-12-04",
    "seen_on": "2026-03-23"
  },
  "1f5d3058fb50c8f46b65befcd4a87ff6": {
    "title": "Chinese Research Vessel Shi Yan 6 Returns To Indian Ocean, Destined For Maldives",
    "date": "2026-03-14",
    "seen_on": "2026-03-23"
  },
  "3a7096d37c9db0d14d682d9042135ff1": {
    "title": "India, China Step Up Outreach To Tarique Rahman's Bangladesh Government",
    "date": "2026-02-23",
    "seen_on": "2026-03-23"
  },
  "7cdfdd8649d85532396bcb92e439e526": {
    "title": "India roundup: India eyes key hub for semiconductors, clean energy, and advanced",
    "date": "2026-03-23",
    "seen_on": "2026-03-23"
  },
  "25600987bb9a853943c165d107f4d56b": {
    "title": "The Oil Trap: Does India’s Growth Story Have a Hidden Expiry Date?",
    "date": "2026-03-20",
    "seen_on": "2026-03-23"
  },
  "dd248ad808e2fc839aa7b48f0ddef719": {
    "title": "Can India Become a Self-Reliant Space Power?",
    "date": "2025-10-16",
    "seen_on": "2026-03-23"
  },
  "1054b7250f0d552c144cfd7dc2c27171": {
    "title": "CERC Approves Tariffs For 2.4 GW Wind-Solar Hybrid Projects To Boost India’s Cle",
    "date": "2026-03-23",
    "seen_on": "2026-03-23"
  },
  "fbc476b836582857f9b270fc4f0be92d": {
    "title": "Chinese ship docks in Sri Lanka despite India, US concerns",
    "date": "2026-03-08",
    "seen_on": "2026-03-23"
  },
  "91f48e840b73995c51fe90a02c5a9e1e": {
    "title": "New monastery project begins near India-China border in Arunachal",
    "date": "2026-02-24",
    "seen_on": "2026-03-23"
  },
  "0f37daf4c88417192acf82152694b869": {
    "title": "India's FDI reset opens controlled door to Chinese participation in semiconducto",
    "date": "2026-03-23",
    "seen_on": "2026-03-23"
  },
  "3cefe1b1cfaf0d2f00bbefff45a7b130": {
    "title": "‘India can play key role in breaking China’s near-monopoly on critical minerals’",
    "date": "2026-03-23",
    "seen_on": "2026-03-23"
  },
  "2c7d0462ece9d5e84f3ed01ad140be29": {
    "title": "India Crude Oil Supply Security & Strategic Reserves",
    "date": "2026-03-23",
    "seen_on": "2026-03-23"
  },
  "4f0429ba0956fa122caa3f39b9713f76": {
    "title": "China rejects India’s claim of sovereign infringement by its BRI projects with P",
    "date": "2026-01-14",
    "seen_on": "2026-03-23"
  },
  "5e520d9b88a519560992cbaa51e828e8": {
    "title": "India-Pakistan Conflict Highlights: “Bharat Will Not Be Deterred By Nuclear Blac",
    "date": "2026-03-14",
    "seen_on": "2026-03-23"
  },
  "cfc42c451a79d60c49a351a40deba280": {
    "title": "'India can play key role in breaking China's near-monopoly on critical minerals'",
    "date": "2026-03-21",
    "seen_on": "2026-03-23"
  },
  "ecfff10620cfeb80313358303f88e36d": {
    "title": "Coal gasification to play key role in India's energy security: G Kishan Reddy",
    "date": "2026-03-23",
    "seen_on": "2026-03-23"
  },
  "47477ed993d3a0f8f9368d1669115790": {
    "title": "'Water bomb': China building world's most powerful mega dam in the Himalayas — h",
    "date": "2025-12-18",
    "seen_on": "2026-03-23"
  },
  "bec1a0f52d16fa17dc2c74f5c69e536e": {
    "title": "India: ACME Solar commissions 480MWh of BESS, readies for FDRE and peak supply d",
    "date": "2026-03-23",
    "seen_on": "2026-03-23"
  },
  "7172e93bb9a4e5da3f8784fe04f1e4e5": {
    "title": "Rethinking India’s Energy Security And A Window For Cooperation – OpEd",
    "date": "2026-03-23",
    "seen_on": "2026-03-23"
  },
  "5b8eafac334ab7e8796d9f2c5eb8d154": {
    "title": "United Kingdom joins Germany, China, Russia, India in Leading Maldives Recovery ",
    "date": "2026-03-24",
    "seen_on": "2026-03-24"
  },
  "2064285c0d93949a1c2cedeacee1ef24": {
    "title": "Taiwanese supply-chain implications as India doubles down on semiconductor incen",
    "date": "2026-03-24",
    "seen_on": "2026-03-24"
  },
  "51048beff925e812f703da0eae363155": {
    "title": "India’s limited oil buffers, reliance on subsidies heighten risks from Middle Ea",
    "date": "2026-03-23",
    "seen_on": "2026-03-24"
  },
  "f922d6908c02caabcbeb84c8dc7e56c1": {
    "title": "India Tightens Scrutiny on Chinese FDI Amid Pakistan Tensions",
    "date": "2025-05-14",
    "seen_on": "2026-03-24"
  },
  "bf34b5a61d2122000028f72f3077e4b7": {
    "title": "India's Path to AI Leadership: An Alternative AI Governance to U.S.-China Compet",
    "date": "2025-10-09",
    "seen_on": "2026-03-24"
  },
  "e1ef2884bde47c594b261a04a9d8eaa8": {
    "title": "Inefficient Renewables? Coal Plant Revival as India Prepares for 270 GW Summer D",
    "date": "2026-03-23",
    "seen_on": "2026-03-24"
  },
  "1793a42746e38214a9ffc6dc8baa49c7": {
    "title": "Coal India Board Approves ₹3160 Crore Guarantee for Subsidiary's Solar Power Pro",
    "date": "2026-03-23",
    "seen_on": "2026-03-24"
  },
  "1ece4ccf64954b4e79dbdd19ffe85bf6": {
    "title": "Bangladesh Now Aligns With China, India Worries",
    "date": "2025-10-26",
    "seen_on": "2026-03-24"
  },
  "6453d5847811168c0cdb3ee1a33fe0d6": {
    "title": "'Severe setback for India': Congress on reports of Pakistan mediation in West As",
    "date": "2026-03-24",
    "seen_on": "2026-03-24"
  },
  "cc4135fe9616e4b86f6291a204d8d2f8": {
    "title": "US targets China’s debt reach in India’s neighborhood",
    "date": "2026-03-21",
    "seen_on": "2026-03-24"
  },
  "96fe83948fb1fcb64fda018d2795f529": {
    "title": "India Strengthens Transmission Infrastructure to Integrate Renewable Energy",
    "date": "2026-03-24",
    "seen_on": "2026-03-24"
  },
  "4a8f78b770df8811284ab9fe7c113eda": {
    "title": "After Yunus cosies up to China, India terminates trans-shipment facility for Ban",
    "date": "2026-03-23",
    "seen_on": "2026-03-24"
  },
  "54c499f7f2e1b648efbfc61676e9359e": {
    "title": "Coal India Approves ₹3,160 Cr Guarantee For 875 MW Solar JV Project",
    "date": "2026-03-24",
    "seen_on": "2026-03-24"
  },
  "5769a84535604a5c63b57dffac6680bf": {
    "title": "India rises as global chip design hub amid supply chain shifts",
    "date": "2026-03-24",
    "seen_on": "2026-03-24"
  },
  "061d4d39c3aeb65db7624e5a36c02246": {
    "title": "India’s Strategic Petroleum Reserves: Hidden Energy Risk",
    "date": "2026-03-24",
    "seen_on": "2026-03-24"
  },
  "ca970c866f5ce274110664debccb1258": {
    "title": "China’s BRI is unprofitable, and still irresistible to India’s neighbours",
    "date": "2025-10-16",
    "seen_on": "2026-03-24"
  },
  "54edacd1a31f5b1a5480ec93f3c3692a": {
    "title": "India-China Engage in War of Words Over Arunachal Pradesh",
    "date": "2025-12-03",
    "seen_on": "2026-03-24"
  },
  "438155d06ece21c52dc26aeca790dc4b": {
    "title": "Look: World's biggest renewable energy 'beast' rising in India — latest update",
    "date": "2026-03-23",
    "seen_on": "2026-03-24"
  },
  "fa90963dac59a634a0ae5c158f7c75f9": {
    "title": "Opinion | Between Washington And Beijing, India Is Quietly Rewriting The Space R",
    "date": "2025-12-29",
    "seen_on": "2026-03-24"
  },
  "a0cb758158a5973e7df38e116bd16476": {
    "title": "Hambantota Port, History, Features, Strategic Concerns for India",
    "date": "2026-03-25",
    "seen_on": "2026-03-26"
  },
  "b1235e41d2c3293b1e203ea7fc388fe3": {
    "title": "Nepal’s new political generation and the India-China contest for influence",
    "date": "2026-03-20",
    "seen_on": "2026-03-26"
  },
  "3dd08aec18dab995f6ff156ace76154a": {
    "title": "Maldives at the Crossroads: Implications for India’s Maritime Strategic Interest",
    "date": "2025-09-05",
    "seen_on": "2026-03-26"
  },
  "ac25c90639b95b65c470927ebda50a44": {
    "title": "Muizzu's U-turn: India in, China out? Maldives seemingly pivots again as PM Modi",
    "date": "2025-07-26",
    "seen_on": "2026-03-26"
  },
  "cdd552c7a6f6f1fb02b69ebf70079b5e": {
    "title": "Iran: Vessels from China, Russia, Pakistan, Iraq, India, Bangladesh, and other c",
    "date": "2026-03-26",
    "seen_on": "2026-03-26"
  },
  "c246d086127b5cd1f69eda3f707cca4d": {
    "title": "India remains engaged with US on Chabahar Port sanctions; meets $120 million obl",
    "date": "2026-03-24",
    "seen_on": "2026-03-26"
  },
  "7ff4b79447d5d5a92c036cca67c9bfda": {
    "title": "India Says No Further Financial Commitment To Chabahar As US Extends Sanctions W",
    "date": "2026-03-25",
    "seen_on": "2026-03-26"
  },
  "d1877d161437826b0d74db236dac55ae": {
    "title": "West Asia War pushes up real cost of India’s semiconductor plans",
    "date": "2026-03-26",
    "seen_on": "2026-03-26"
  },
  "6c0b9cb700ebe80b3a9ad79989b0c85f": {
    "title": "How India is reducing dependence on China for rare earth minerals",
    "date": "2026-03-25",
    "seen_on": "2026-03-26"
  },
  "945fe9d8156c52823f903af4cc6c32fd": {
    "title": "Why India lost out to China in the rare-earths race",
    "date": "2025-11-08",
    "seen_on": "2026-03-26"
  },
  "1ea30e999014a70503ca24f6f89d5d5d": {
    "title": "India, China, and How Not to Save the Brahmaputra",
    "date": "2026-03-24",
    "seen_on": "2026-03-26"
  },
  "ea81a4a569e72a3acf68cecb3ac34188": {
    "title": "Climate Threatens India's Food Security: Study Warns",
    "date": "2026-03-25",
    "seen_on": "2026-03-26"
  },
  "58a0ec8e5e9d4285ab0c9be8c663cf2d": {
    "title": "India is not just a market; it is a mindset — Journey in a transforming solar la",
    "date": "2026-03-26",
    "seen_on": "2026-03-26"
  },
  "12883000dcb9eeea8745588cc6f1d92a": {
    "title": "Ceigall India signs PPAs for 337 MW solar projects",
    "date": "2026-03-26",
    "seen_on": "2026-03-26"
  },
  "f2535954024a5f4d181e3836dd07294d": {
    "title": "China’s Xinjiang Policy: The Imperative for India",
    "date": "2021-05-12",
    "seen_on": "2026-03-26"
  },
  "138066283d14d86f2476c080bab901b3": {
    "title": "Rare Earths Armistice: India’s Shift from Mining to Processing",
    "date": "2025-11-12",
    "seen_on": "2026-03-26"
  },
  "3ada0bc95470af6d589967c3d9f1b935": {
    "title": "Would New PM Shake Nepal's Delicate India-China Balance? What Experts Said",
    "date": "2026-02-26",
    "seen_on": "2026-03-26"
  },
  "f9b28fc6c7882a86ecf658ab4897b6c1": {
    "title": "Blueleaf Energy switches on 300-MWp wind-solar hybrid in India",
    "date": "2026-03-26",
    "seen_on": "2026-03-26"
  },
  "70213026c2a8f7f543ccbae72181c042": {
    "title": "China ran campaign to discredit French Rafale fighter after India-Pakistan confl",
    "date": "2025-11-20",
    "seen_on": "2026-03-26"
  },
  "ff9b3f67875dfd3025982bb538587c73": {
    "title": "Silence Is Not Strategy: How India Blinked on Iran",
    "date": "2026-03-22",
    "seen_on": "2026-03-26"
  },
  "a6a5ae07f86e1559d79ceb320504351d": {
    "title": "'India can play key role in breaking China's near-monopoly on critical minerals'",
    "date": "2026-03-22",
    "seen_on": "2026-03-26"
  },
  "eeea96ab6ae57e57c4f6cb0b3b39067d": {
    "title": "Nepal Between Giants: India–China Rivalry in the Himalayas",
    "date": "2025-10-03",
    "seen_on": "2026-03-26"
  },
  "a4192f01e0cfaf0b50f8a4833a6ccc8e": {
    "title": "Lipulekh Pass reopening signals India-China thaw amid Nepal territorial concerns",
    "date": "2026-03-20",
    "seen_on": "2026-03-26"
  },
  "1225473d66a72595f83f1ec7125ed9b1": {
    "title": "China set to widen footprint in Bangladesh as India's ties decline",
    "date": "2026-02-09",
    "seen_on": "2026-03-26"
  },
  "840c8a7bdc44dc065cac94cfaa62b2b0": {
    "title": "From mines to magnets: How India plans to counter China’s rare earth grip | The ",
    "date": "2026-03-03",
    "seen_on": "2026-03-26"
  },
  "4d43f7eca274b255657eaff1945b3117": {
    "title": "Renewable Energy in India, Sectors, Initiatives, Significance",
    "date": "2026-03-25",
    "seen_on": "2026-03-26"
  },
  "2fec4fc149ee5f1859587df94c679a37": {
    "title": "Japan in talks with India to explore for rare earths, sources say",
    "date": "2026-03-02",
    "seen_on": "2026-03-27"
  },
  "c6c7db71eb435df06037f3841e5e3b96": {
    "title": "China-Pakistan economic corridor to expand into Afghanistan: Why it matters for ",
    "date": "2026-03-25",
    "seen_on": "2026-03-27"
  }
}